labellines/__init__.py
labellines/core.py
labellines/line_label.py
labellines/test.py
labellines/utils.py
labellines/baseline/test_align.png
labellines/baseline/test_auto_layout.png
labellines/baseline/test_dateaxis_advanced.png
labellines/baseline/test_dateaxis_naive.png
labellines/baseline/test_errorbar.png
labellines/baseline/test_errorbar_with_list.png
labellines/baseline/test_label_datetime_plot.png
labellines/baseline/test_label_range.png
labellines/baseline/test_labeling_axhline.png
labellines/baseline/test_labels_range.png
labellines/baseline/test_linspace.png
labellines/baseline/test_negative_spacing.png
labellines/baseline/test_non_uniform_and_negative_spacing.png
labellines/baseline/test_outline.png
labellines/baseline/test_polar.png
labellines/baseline/test_rotation.png
labellines/baseline/test_rotation_correction.png
labellines/baseline/test_vertical.png
labellines/baseline/test_xlogspace.png
labellines/baseline/test_xylogspace.png
labellines/baseline/test_ylogspace.png
matplotlib_label_lines-0.8.0.dist-info/METADATA
matplotlib_label_lines-0.8.0.dist-info/WHEEL
matplotlib_label_lines-0.8.0.dist-info/licenses/LICENSE
matplotlib_label_lines-0.8.0.dist-info/RECORD
